masterpiece_pahomqtt/__init__.py
masterpiece_pahomqtt/pahomqtt.py
masterpiece_pahomqtt/py.typed
masterpiece_pahomqtt-0.1.11.dist-info/licenses/LICENSE.rst
masterpiece_pahomqtt-0.1.11.dist-info/METADATA
masterpiece_pahomqtt-0.1.11.dist-info/WHEEL
masterpiece_pahomqtt-0.1.11.dist-info/entry_points.txt
masterpiece_pahomqtt-0.1.11.dist-info/top_level.txt
masterpiece_pahomqtt-0.1.11.dist-info/RECORD
